env_var_config/__init__.py
env_var_config/config.py
env_var_config-0.1.0.dist-info/METADATA
env_var_config-0.1.0.dist-info/RECORD
env_var_config-0.1.0.dist-info/WHEEL
env_var_config-0.1.0.dist-info/top_level.txt
