Metadata-Version: 2.1
Name: env-var-config
Version: 0.1.0
Summary: Parsing configuration from environment variables as typing.NamedTuple
Home-page: https://github.com/iteriodata/env_var_config
Author: UNKNOWN
Author-email: UNKNOWN
License: MIT
Project-URL: Bug Reports, https://github.com/iteriodata/env_var_config/issues
Project-URL: Source, https://github.com/iteriodata/env_var_config
Keywords: config env var
Platform: UNKNOWN
Classifier: Programming Language :: Python :: 3.6
Classifier: Operating System :: OS Independent
Classifier: License :: OSI Approved :: MIT License
Classifier: Development Status :: 4 - Beta
Classifier: Intended Audience :: Developers
Classifier: Natural Language :: English
